command_lifecycle/__init__.py
command_lifecycle/buffer.py
command_lifecycle/helpers.py
command_lifecycle/lifecycle.py
command_lifecycle/timeout.py
command_lifecycle/wakeword.py
command_lifecycle-4.1.0.dist-info/LICENSE
command_lifecycle-4.1.0.dist-info/METADATA
command_lifecycle-4.1.0.dist-info/WHEEL
command_lifecycle-4.1.0.dist-info/top_level.txt
command_lifecycle-4.1.0.dist-info/RECORD
