Metadata-Version: 2.1
Name: command-lifecycle
Version: 4.1.0
Summary: Python library to manage the life-cycle of voice commands.
Home-page: https://github.com/richtier/voice-command-lifecycle
Author: Richard Tier
Author-email: rikatee@gmail.com
License: MIT
Platform: UNKNOWN
Classifier: Development Status :: 4 - Beta
Classifier: Environment :: Console
Classifier: Intended Audience :: Developers
Classifier: License :: OSI Approved :: MIT License
Classifier: Natural Language :: English
Classifier: Operating System :: OS Independent
Classifier: Programming Language :: Python :: 3.6
Classifier: Programming Language :: Python :: Implementation :: PyPy
Classifier: Topic :: Software Development :: Libraries :: Python Modules
Requires-Dist: resettabletimer (<1.0.0,>=0.6.3)
Provides-Extra: test
Requires-Dist: pytest (==3.2.3) ; extra == 'test'
Requires-Dist: pytest-cov (==2.5.1) ; extra == 'test'
Requires-Dist: pytest-sugar (==0.9.0) ; extra == 'test'
Requires-Dist: flake8 (==3.4.0) ; extra == 'test'
Requires-Dist: codecov (==2.0.9) ; extra == 'test'
Requires-Dist: twine (<2.0.0,>=1.11.0) ; extra == 'test'
Requires-Dist: wheel (<1.0.0,>=0.31.0) ; extra == 'test'
Requires-Dist: setuptools (<39.0.0,>=38.6.0) ; extra == 'test'
